./.gitignore
./PKG-INFO
./README.md
./__init__.py
./dimension_reduction.py
./pyproject.toml
./test.py
feluda_dimension_reduction-0.2.0.dist-info/METADATA
feluda_dimension_reduction-0.2.0.dist-info/WHEEL
feluda_dimension_reduction-0.2.0.dist-info/RECORD
